{"name": "redis-rdb-tools", "description": "Parse Redis dump.rdb files, Analyze Memory, and Export Data to JSON", "license": {"key": "mit", "name": "MIT License", "spdx_id": "MIT", "url": "https://api.github.com/licenses/mit"}, "starNum": 2315, "folkNum": 348, "watchNum": 2315, "topic": [], "contributors": ["sripathikrishnan", "oranagra", "mihu", "joshtronic", "amotzg", "yoav-steinberg", "guybe7", "cgordon", "clofresh", "ckrybus", "danni-m", "joshowen", "jdp", "shigeki-hirose", "solso"], "packages": ["os", "setuptools", "distutils", "rdbtools", "unittest", "math"]}