{"name": "qpage", "description": "\ud83d\udc68\u200d\ud83d\udcbb Free Project For Creating  Academic Homepage Without Any Code In 3min", "license": {"key": "mit", "name": "MIT License", "spdx_id": "MIT", "url": "https://api.github.com/licenses/mit"}, "starNum": 80, "folkNum": 24, "watchNum": 80, "topic": ["academic", "academichomepage", "badge", "fast", "fasthtml", "font", "homepage", "html", "icon", "opensource", "python", "python-3", "qpage", "quickpage", "resume-creator", "shorttime", "site-generator", "static-site-generation", "website-generation", "websitebuilder"]}